dingsdk/__init__.py
dingsdk/core.py
dingsdk/main.py
dingsdk/libs/__init__.py
dingsdk/libs/access_token.py
dingsdk/libs/applink.py
dingsdk/libs/approval.py
dingsdk/libs/attendance.py
dingsdk/libs/chatbots.py
dingsdk/libs/contacts.py
dingsdk/libs/personnel.py
dingsdk/libs/tasktodo.py
dingsdk/utils/__init__.py
dingsdk/utils/instance_cleaner.py
dingsdk-2.0.0.dist-info/LICENSE
dingsdk-2.0.0.dist-info/LICENSE-APACHE
dingsdk-2.0.0.dist-info/LICENSE-MIT
dingsdk-2.0.0.dist-info/METADATA
dingsdk-2.0.0.dist-info/WHEEL
dingsdk-2.0.0.dist-info/top_level.txt
dingsdk-2.0.0.dist-info/RECORD
