Metadata-Version: 2.1
Name: dingsdk
Version: 2.0.0
Summary: DingTalk Mini SDK
Author-email: "Mr.LLT" <lltemail@dingtalk.com>
Classifier: Intended Audience :: Developers
Classifier: Programming Language :: Python :: 3
Classifier: License :: OSI Approved :: MIT License
Classifier: Development Status :: 5 - Production/Stable
Classifier: Topic :: Office/Business :: Office Suites
Classifier: Topic :: Scientific/Engineering :: Information Analysis
Requires-Python: >=3.7
License-File: LICENSE
License-File: LICENSE-APACHE
License-File: LICENSE-MIT
Requires-Dist: requests (==2.28.*)
